rutificador/__init__.py
rutificador/cli.py
rutificador/config.py
rutificador/exceptions.py
rutificador/formatter.py
rutificador/procesador.py
rutificador/rut.py
rutificador/utils.py
rutificador/validador.py
rutificador/version.py
rutificador-1.0.19.dist-info/METADATA
rutificador-1.0.19.dist-info/WHEEL
rutificador-1.0.19.dist-info/entry_points.txt
rutificador-1.0.19.dist-info/licenses/LICENSE
rutificador-1.0.19.dist-info/RECORD
