Metadata-Version: 2.4
Name: rutificador
Version: 1.0.19
Summary: Herramientas para validar, calcular y formatear el Rol Único Tributario (RUT) en Chile, con procesamiento por lotes y salida en múltiples formatos.
License: MIT
License-File: LICENSE
Keywords: RUT,Chile,validación,formateo,librería,id,rutificador,rut-chile
Author: Carlos Ortega González
Author-email: carlosortega77@gmail.com
Requires-Python: >=3.9,<4.0
Classifier: Development Status :: 5 - Production/Stable
Classifier: Intended Audience :: Developers
Classifier: License :: OSI Approved :: MIT License
Classifier: Programming Language :: Python :: 3
Classifier: Programming Language :: Python :: 3.9
Classifier: Programming Language :: Python :: 3.10
Classifier: Programming Language :: Python :: 3.11
Classifier: Programming Language :: Python :: 3.12
Classifier: Programming Language :: Python :: 3.13
Classifier: Programming Language :: Python :: 3.14
Classifier: Programming Language :: Python :: 3 :: Only
Classifier: Topic :: Software Development :: Libraries :: Python Modules
Classifier: Topic :: Utilities
Requires-Dist: tomli (>=2.0,<3.0) ; python_version < "3.11"
Project-URL: Homepage, https://pypi.org/project/rutificador/
Project-URL: Repository, https://github.com/cortega26/rutificador
